snews/__init__.py
snews/__main__.py
snews/__version__.py
snews/data/SNEWS World Map - Points.json
snews/data/__init__.py
snews/data/detectors/Super-Kamiokande.json
snews/data/detectors/__init__.py
snews/data/detectors/draft/Baksan.json
snews/data/detectors/draft/Borexino.json
snews/data/detectors/draft/DARWIN.json
snews/data/detectors/draft/DUNE.json
snews/data/detectors/draft/DarkSide-20k.json
snews/data/detectors/draft/DarkSide-50.json
snews/data/detectors/draft/DayaBay.json
snews/data/detectors/draft/HALO-1kT.json
snews/data/detectors/draft/HALO.json
snews/data/detectors/draft/Hyper-Kamiokande.json
snews/data/detectors/draft/IceCube.json
snews/data/detectors/draft/JUNO.json
snews/data/detectors/draft/KM3NeT.json
snews/data/detectors/draft/KamLAND.json
snews/data/detectors/draft/LVD.json
snews/data/detectors/draft/LZ.json
snews/data/detectors/draft/NOvA.json
snews/data/detectors/draft/PandaX.json
snews/data/detectors/draft/SNOplus.json
snews/data/detectors/draft/XENONnT.json
snews/data/io.py
snews/data/mock/__init__.py
snews/data/mock/coincidence_scenarios.json
snews/data/mock/time_formats.json
snews/data/timing/__init__.py
snews/data/timing/leap_seconds.json
snews/data/utilities.py
snews/examples/tutorial.ipynb
snews/models/__init__.py
snews/models/detectors.py
snews/models/messages.py
snews/models/timing.py
snews/schema/CoincidenceTierMessage.schema.json
snews/schema/Detector.schema.json
snews/schema/HeartbeatMessage.schema.json
snews/schema/RetractionMessage.schema.json
snews/schema/SignificanceTierMessage.schema.json
snews/schema/TimingTierMessage.schema.json
snews/schema/__init__.py
snews_data_formats-1.0.0.dist-info/LICENSE
snews_data_formats-1.0.0.dist-info/METADATA
snews_data_formats-1.0.0.dist-info/WHEEL
snews_data_formats-1.0.0.dist-info/entry_points.txt
snews_data_formats-1.0.0.dist-info/RECORD
