Metadata-Version: 2.1
Name: snews-data-formats
Version: 1.0.0
Summary: A unified collection of SNEWS data, models, and schema
Home-page: https://github.com/SNEWS2/snews-data-formats
License: BSD 3-Clause
Author: SNEWS Collaboration
Author-email: snews2.0@lists.bnl.gov
Maintainer: Justin Vasel
Maintainer-email: justin.vasel@gmail.com
Requires-Python: >=3.9,<3.13
Classifier: License :: Other/Proprietary License
Classifier: Programming Language :: Python :: 3
Classifier: Programming Language :: Python :: 3.9
Classifier: Programming Language :: Python :: 3.10
Classifier: Programming Language :: Python :: 3.11
Requires-Dist: numpy (>=1.26.3,<2.0.0)
Requires-Dist: pycountry (>=22.3.5,<23.0.0)
Requires-Dist: pydantic (>=2.4.2,<3.0.0)
Requires-Dist: pydantic-extra-types (>=2.1.0,<3.0.0)
Requires-Dist: single-version (>=1.6.0,<2.0.0)
Project-URL: Repository, https://github.com/SNEWS2/snews-data-formats
